flask_newui-1.0.0.dist-info/licenses/LICENSE
newui/__init__.py
newui/cli.py
newui/components.py
newui/composition.py
newui/devtools.py
newui/newui.py
newui/routing.py
newui/stores.py
newui/websocket.py
newui/core/__init__.py
newui/core/ajax.py
newui/core/components.py
newui/core/renderer.py
newui/core/state.py
newui/static/newui.css
newui/static/newui.js
flask_newui-1.0.0.dist-info/METADATA
flask_newui-1.0.0.dist-info/WHEEL
flask_newui-1.0.0.dist-info/entry_points.txt
flask_newui-1.0.0.dist-info/top_level.txt
flask_newui-1.0.0.dist-info/RECORD
