Metadata-Version: 2.4
Name: flask-newui
Version: 1.0.0
Summary: A modern reactive frontend framework that bridges Flask/Jinja2 with modern UI capabilities
Author-email: NewUI Contributors <contact@flask-newui.dev>
Maintainer-email: NewUI Contributors <contact@flask-newui.dev>
License: MIT License
Project-URL: Homepage, https://github.com/smbrandonjr/flask-newui
Project-URL: Documentation, https://flask-newui.dev/docs
Project-URL: Repository, https://github.com/smbrandonjr/flask-newui
Project-URL: Bug Reports, https://github.com/smbrandonjr/flask-newui/issues
Project-URL: Changelog, https://github.com/smbrandonjr/flask-newui/blob/main/CHANGELOG.md
Keywords: flask,jinja2,frontend,framework,reactive,ui,components
Classifier: Development Status :: 5 - Production/Stable
Classifier: Intended Audience :: Developers
Classifier: Topic :: Internet :: WWW/HTTP :: Dynamic Content
Classifier: Topic :: Software Development :: Libraries :: Application Frameworks
Classifier: Topic :: Software Development :: Libraries :: Python Modules
Classifier: Topic :: Software Development :: User Interfaces
Classifier: License :: OSI Approved :: MIT License
Classifier: Programming Language :: Python :: 3
Classifier: Programming Language :: Python :: 3.7
Classifier: Programming Language :: Python :: 3.8
Classifier: Programming Language :: Python :: 3.9
Classifier: Programming Language :: Python :: 3.10
Classifier: Programming Language :: Python :: 3.11
Classifier: Programming Language :: Python :: 3.12
Classifier: Framework :: Flask
Classifier: Environment :: Web Environment
Classifier: Operating System :: OS Independent
Requires-Python: >=3.7
License-File: LICENSE
Requires-Dist: Flask>=1.1.0
Requires-Dist: Jinja2>=2.11.0
Requires-Dist: MarkupSafe>=2.0.0
Provides-Extra: websocket
Requires-Dist: Flask-SocketIO>=5.0.0; extra == "websocket"
Provides-Extra: dev
Requires-Dist: pytest>=6.0; extra == "dev"
Requires-Dist: pytest-flask>=1.0; extra == "dev"
Requires-Dist: pytest-cov>=2.0; extra == "dev"
Requires-Dist: black>=21.0; extra == "dev"
Requires-Dist: flake8>=3.9; extra == "dev"
Requires-Dist: mypy>=0.900; extra == "dev"
Requires-Dist: pre-commit>=2.0; extra == "dev"
Provides-Extra: examples
Requires-Dist: Flask-SocketIO>=5.0.0; extra == "examples"
Provides-Extra: all
Requires-Dist: Flask-SocketIO>=5.0.0; extra == "all"
Requires-Dist: pytest>=6.0; extra == "all"
Requires-Dist: pytest-flask>=1.0; extra == "all"
Requires-Dist: pytest-cov>=2.0; extra == "all"
Requires-Dist: black>=21.0; extra == "all"
Requires-Dist: flake8>=3.9; extra == "all"
Requires-Dist: mypy>=0.900; extra == "all"
Requires-Dist: pre-commit>=2.0; extra == "all"
Dynamic: license-file
